LICENSE.md
MANIFEST.in
README.md
setup.cfg
setup.py
drf_hcaptcha/__init__.py
drf_hcaptcha/apps.py
drf_hcaptcha/checks.py
drf_hcaptcha/client.py
drf_hcaptcha/constants.py
drf_hcaptcha/fields.py
drf_hcaptcha/validators.py
drf_hcaptcha.egg-info/PKG-INFO
drf_hcaptcha.egg-info/SOURCES.txt
drf_hcaptcha.egg-info/dependency_links.txt
drf_hcaptcha.egg-info/not-zip-safe
drf_hcaptcha.egg-info/requires.txt
drf_hcaptcha.egg-info/top_level.txt